glow_navigator/__init__.py
glow_navigator/glow_config.py
glow_navigator/glow_navigator.py
glow_navigator/glow_settings.yaml
glow_navigator/glow_utils.py
glow_navigator-1.24.1.dist-info/DESCRIPTION.rst
glow_navigator-1.24.1.dist-info/METADATA
glow_navigator-1.24.1.dist-info/RECORD
glow_navigator-1.24.1.dist-info/WHEEL
glow_navigator-1.24.1.dist-info/entry_points.txt
glow_navigator-1.24.1.dist-info/metadata.json
glow_navigator-1.24.1.dist-info/top_level.txt
