Metadata-Version: 2.0
Name: glow-navigator
Version: 1.24.1
Summary: Tool for navigating Glow object relationships
Home-page: https://github.com/thoughtcroft/glow_navigator
Author: Warren bain
Author-email: warren@thoughtcroft.com
License: MIT
Keywords: directed-graph
Platform: UNKNOWN
Classifier: Development Status :: 3 - Alpha
Classifier: Intended Audience :: Developers
Classifier: Topic :: Software Development
Classifier: License :: OSI Approved :: MIT License
Classifier: Programming Language :: Python :: 2
Classifier: Programming Language :: Python :: 2.7
Provides-Extra: test
Requires-Dist: click
Requires-Dist: colorama
Requires-Dist: future
Requires-Dist: networkx (==1.11)
Requires-Dist: pyreadline
Requires-Dist: pyyaml
Requires-Dist: termcolor
Provides-Extra: test
Requires-Dist: coverage; extra == 'test'
Requires-Dist: ddt; extra == 'test'
Requires-Dist: pylint; extra == 'test'
Requires-Dist: pytest; extra == 'test'
